shadowsocks_check/__init__.py
shadowsocks_check-0.3.dist-info/METADATA
shadowsocks_check-0.3.dist-info/RECORD
shadowsocks_check-0.3.dist-info/WHEEL
shadowsocks_check-0.3.dist-info/entry_points.txt
shadowsocks_check-0.3.dist-info/top_level.txt
